face_verify/__init__.py
face_verify/cli.py
face_verify/face_verify.py
face_verify-1.0.3.dist-info/LICENSE
face_verify-1.0.3.dist-info/METADATA
face_verify-1.0.3.dist-info/WHEEL
face_verify-1.0.3.dist-info/entry_points.txt
face_verify-1.0.3.dist-info/top_level.txt
face_verify-1.0.3.dist-info/RECORD
