Metadata-Version: 2.1
Name: face-verify
Version: 1.0.3
Summary: Recognize face for web library
Home-page: https://github.com/wielqus/face_verify
Author: Jakub Wielgus
Author-email: wielqus@gmail.com
License: MIT license
Keywords: face_verify
Platform: UNKNOWN
Classifier: Development Status :: 2 - Pre-Alpha
Classifier: Intended Audience :: Developers
Classifier: License :: OSI Approved :: MIT License
Classifier: Natural Language :: English
Classifier: Programming Language :: Python :: 3
Classifier: Programming Language :: Python :: 3.5
Classifier: Programming Language :: Python :: 3.6
Classifier: Programming Language :: Python :: 3.7
Classifier: Programming Language :: Python :: 3.8
Requires-Python: >=3.5
Requires-Dist: Click (>=7.0)
Requires-Dist: Pillow
Requires-Dist: dlib
Requires-Dist: face-recognition-models
